{
  "name": "bootstrap-select",
  "main": "bootstrap-select.js",
  "version": "1.3.3",
  "homepage": "https://github.com/silviomoreto/bootstrap-select",
  "authors": [
    "silviomoreto"
  ],
  "keywords": [
    "form",
    "bootstrap",
    "select",
    "replacement"
  ],
  "dependencies": {
    "jquery": ">=1.7"
  },
  "license": "MIT",
  "ignore": [
    "**/.*",
    "node_modules",
    "bower_components",
    "test",
    "tests"
  ],
  "_release": "1.3.3",
  "_resolution": {
    "type": "version",
    "tag": "1.3.3",
    "commit": "a27b06eb54c870637d5e867753109881ae459d7f"
  },
  "_source": "git://github.com/silviomoreto/bootstrap-select.git",
  "_target": "*",
  "_originalSource": "bootstrap-select"
}